setup.py
hart2006_probability/Binomialdistribution.py
hart2006_probability/Gaussiandistribution.py
hart2006_probability/Generaldistribution.py
hart2006_probability/__init__.py
hart2006_probability.egg-info/PKG-INFO
hart2006_probability.egg-info/SOURCES.txt
hart2006_probability.egg-info/dependency_links.txt
hart2006_probability.egg-info/not-zip-safe
hart2006_probability.egg-info/top_level.txt