Metadata-Version: 2.1
Name: hart2006-probability
Version: 0.1
Summary: Gaussian and Binomial distributions
Home-page: UNKNOWN
Author: Michael Hart
License: UNKNOWN
Platform: UNKNOWN
